hscquery.py
hscquery-0.2.1.dist-info/LICENSE
hscquery-0.2.1.dist-info/METADATA
hscquery-0.2.1.dist-info/WHEEL
hscquery-0.2.1.dist-info/top_level.txt
hscquery-0.2.1.dist-info/RECORD
