Metadata-Version: 2.1
Name: hscquery
Version: 0.2.1
Summary: Module for accessing the HSC-SSP database
Home-page: https://github.com/ruizca/hscquery
Author: Angel Ruiz
Author-email: angel.ruizca@gmail.com
License: UNKNOWN
Platform: UNKNOWN
Classifier: Development Status :: 4 - Beta
Classifier: Intended Audience :: Science/Research
Classifier: Topic :: Scientific/Engineering :: Astronomy
Classifier: Topic :: Database :: Front-Ends
Classifier: Programming Language :: Python :: 2.7
Classifier: Programming Language :: Python :: 3.6
Classifier: License :: OSI Approved :: BSD License
Classifier: Operating System :: POSIX :: Linux
Requires-Dist: astropy
Requires-Dist: future
